eoq3/__init__.py
eoq3/accesscontroller/__init__.py
eoq3/accesscontroller/accesscontroller.py
eoq3/accesscontroller/noaccesscontroller.py
eoq3/accesscontroller/permissions.py
eoq3/command/__init__.py
eoq3/command/command.py
eoq3/concepts/__init__.py
eoq3/concepts/concepts.py
eoq3/concepts/gen/generateconcepts.py
eoq3/config/__init__.py
eoq3/config/config.py
eoq3/domain/__init__.py
eoq3/domain/domain.py
eoq3/domain/domainconnector.py
eoq3/domainwithmdb/__init__.py
eoq3/domainwithmdb/change.py
eoq3/domainwithmdb/cloner.py
eoq3/domainwithmdb/cmdrunner.py
eoq3/domainwithmdb/conceptwalker.py
eoq3/domainwithmdb/constraintverifier.py
eoq3/domainwithmdb/deleter.py
eoq3/domainwithmdb/domainwithmdb.py
eoq3/domainwithmdb/history.py
eoq3/domainwithmdb/qryrunner.py
eoq3/domainwithmdb/querywatcher.py
eoq3/domainwithmdb/session.py
eoq3/domainwithmdb/transaction.py
eoq3/domainwithmdb/util.py
eoq3/domainwithmdb/verifiedmdb.py
eoq3/domainwithmdb/gen/generatecloner.py
eoq3/domainwithmdb/gen/generateconceptwalker.py
eoq3/domainwithmdb/gen/generatedeleter.py
eoq3/domainwrappers/__init__.py
eoq3/domainwrappers/domainpool.py
eoq3/domainwrappers/domaintoprocesswrapper.py
eoq3/domainwrappers/multiprocessingdomainclient.py
eoq3/domainwrappers/multiprocessingdomainhost.py
eoq3/domainwrappers/queuebasedframecom.py
eoq3/domainwrappers/remotedomainbasea.py
eoq3/domainwrappers/remotedomainclient.py
eoq3/domainwrappers/remotedomainserver.py
eoq3/domainwrappers/serialdomain.py
eoq3/error/__init__.py
eoq3/error/error.py
eoq3/examples/__init__.py
eoq3/examples/warehouse.py
eoq3/frame/__init__.py
eoq3/frame/frame.py
eoq3/logger/__init__.py
eoq3/logger/compoundlogger.py
eoq3/logger/consoleandfilelogger.py
eoq3/logger/consolelogger.py
eoq3/logger/filelogger.py
eoq3/logger/logger.py
eoq3/logger/nologger.py
eoq3/mdb/__init__.py
eoq3/mdb/mdb.py
eoq3/mdb/readonlymdb.py
eoq3/query/__init__.py
eoq3/query/query.py
eoq3/serializer/__init__.py
eoq3/serializer/jsonserializer.py
eoq3/serializer/jsserializer.py
eoq3-3.1.0.dist-info/licenses/LICENSE
eoq3-3.1.0.dist-info/METADATA
eoq3-3.1.0.dist-info/WHEEL
eoq3-3.1.0.dist-info/top_level.txt
eoq3-3.1.0.dist-info/RECORD
