Metadata-Version: 2.4
Name: eoq3
Version: 3.1.0
Summary: Core implementation of EOQ3 for python
Author-email: Bjoern Annighoefer <bjoern.annighoefer@ils.uni-stuttgart.de>
Project-URL: Homepage, https://gitlab.com/eoq/py/eoq3
Project-URL: Issues, https://gitlab.com/eoq/py/eoq3/-/issues
Classifier: Programming Language :: Python :: 3
Classifier: License :: OSI Approved :: MIT License
Classifier: Operating System :: OS Independent
Requires-Python: >=3.10
License-File: LICENSE
Requires-Dist: antlr4-python3-runtime
Dynamic: license-file
